DataClass/DefectReportConfig.py
DataClass/__init__.py
RCA_Summary-1.0.dist-info/METADATA
RCA_Summary-1.0.dist-info/WHEEL
RCA_Summary-1.0.dist-info/top_level.txt
RCA_Summary-1.0.dist-info/RECORD
